{
	"name": "Sketch Company Color Theme",
	"colors": {
		// editor
		"editor.background": "#04090f",
		"editor.selectionBackground": "#132d4d",
		"editor.lineHighlightBorder": "#132d4d",
		"editor.findMatchHighlightBackground": "#d83aff41",
		"editor.findMatchBackground": "#d83aff41",
		"editor.foreground": "#d0ebee",
		"editorGroup.border": "#0e1e33",
		"editorGroup.dropIntoPromptForeground": "#d0ebee",
		"editorGroup.dropBackground": "#0f274694",
		"editorGroupHeader.tabsBackground": "#060d16",
		"editorCursor.foreground": "#d0ebee",
		"editorError.foreground": "#ff2245",
		"editorInfo.foreground": "#00c076",
		"editorWarning.foreground": "#ffbd2f",
		"editorHint.foreground": "#00c076",
		"editorGhostText.foreground": "#395f85",

		// hover widget
		"editorHoverWidget.background": "#0b1c31",
		"editorHoverWidget.foreground": "#d0ebee",
		"editorHoverWidget.highlightForeground": "#0f2746",
		"editorHoverWidget.border": "#0e1e33",

		// line number
		"editorLineNumber.activeForeground": "#d0ebee",
		"editorLineNumber.foreground": "#5e7a7e",

		"editorWidget.background": "#0b1c31",
		"editorWidget.foreground": "#d0ebee",
		"editorWidget.resizeBorder": "#0e1e33",
		"editorWidget.border": "#0e1e33",

		// suggest widget
		"editorSuggestWidget.background": "#0b1c31",
		"editorSuggestWidget.foreground": "#d0ebee",
		"editorSuggestWidget.selectedBackground": "#0f2746",
		"editorSuggestWidget.border": "#0e1e33",

		// menu
		"menu.background": "#060d16",
		"menu.foreground": "#d0ebee",

		// panel
		"panelTitle.activeBorder": "#00c076",
		"panelTitle.activeForeground": "#d0ebee",
		"panelTitle.inactiveForeground": "#709196",
		"panelInput.border": "#0e1e33",
		"panel.border": "#0e1e33",
		"panel.background": "#060d16",

		"sideBySideEditor.horizontalBorder": "#0e1e33",
		"sideBySideEditor.verticalBorder": "#0e1e33",

		// terminal
		"terminal.background": "#04090f",
		"terminal.foreground": "#d0ebee",
		"terminal.tab.activeBorder": "#00c076",
		"terminal.selectionBackground": "#132d4d",
		"terminal.findMatchBackground": "#d83aff41",
		"terminal.findMatchHighlightBackground": "#d83aff41",
		"terminal.border": "#0e1e33",
		"problemsErrorIcon.foreground": "#ff2245",
		"problemsWarningIcon.foreground": "#ffbd2f",
		"problemsInfoIcon.foreground": "#2fa1ff",
		"outputView.background": "#04090f",
		"debugConsole.sourceForeground": "#d0ebee",
		"debugConsole.errorForeground": "#ff2245",
		"debugConsole.warningForeground": "#ffbd2f",
		"debugConsole.infoForeground": "#2fa1ff",
		"ports.iconRunningProcessForeground": "#d0ebee",

		// dropdown
		"dropdown.background": "#04090f",
		"dropdown.foreground": "#d0ebee",
		"dropdown.border": "#0e1e33",
		"dropdown.listBackground": "#04090f",


		// scrollbar
		"scrollbarSlider.background": "#08111d",
		"scrollbarSlider.hoverBackground": "#0b1c31",
		"scrollbarSlider.activeBackground": "#08111d",


		// badge
		"badge.background": "#1e7ac5",
		"badge.foreground": "#d0ebee",

		// activitybar
		"activityBarBadge.background": "#00c076",
		"activityBar.background": "#08111d",
		"activityBar.border": "#0e1e33",
		"activityBar.activeBackground": "#0b1c31",
		"activityBar.activeBorder": "#d0ebee",
		"activityBar.inactiveForeground": "#506c6e",
		"activityBar.foreground": "#d0ebee",
		"statusBar.background": "#08111d",
		"statusBar.foreground": "#d0ebee",
		"statusBarItem.activeBackground": "#08111d",
		"statusBarItem.errorBackground": "#ff2245",
		"statusBarItem.warningBackground": "#ffbd2f",
		"statusBarItem.prominentBackground": "#1e7ac5",
		"notifications.background": "#08111d",
		"notifications.foreground": "#d0ebee",
		"notifications.border": "#0e1e33",
		"notificationToast.border": "#0e1e33",
		"notificationCenterHeader.background": "#0b1c31",
		"notificationCenterHeader.foreground": "#d0ebee",
		"notificationsErrorIcon.foreground": "#ff2245",
		"notificationsWarningIcon.foreground": "#ffbd2f",
		"notificationsInfoIcon.foreground": "#1e7ac5",
		"notificationCenter.border": "#0e1e33",

		// titlebar
		"titleBar.activeBackground": "#04090f",
		"titleBar.activeForeground": "#d0ebee",
		"titleBar.border": "#0e1e33",
		
		// sidebar
		"sideBarTitle.foreground": "#d0ebee",
		"sideBarTitle.background": "#060d16",
		"sideBar.background": "#060d16",
		"sideBar.border": "#0e1e33",
		"sideBar.dropBackground": "#060d16",
		"sideBarSectionHeader.background": "#0e1e33",
		"sideBarSectionHeader.foreground": "#d0ebee",

		// tab
		"tab.inactiveBackground": "#060d16",
		"tab.activeBackground": "#04090f",
		"tab.activeForeground": "#d0ebee",
		"tab.inactiveForeground": "#9fcfd6",
		"tab.activeBorder": "#04090f",
		"tab.border": "#0e1e33",
		"tab.hoverBackground": "#08111d",
		"tab.activeBorderTop": "#00c076",
		"tab.lastPinnedBorder": "#00c076",

		// input
		"input.background": "#060d16",
		"input.border": "#0e1e33",
		"input.foreground": "#d0ebee",

		"banner.background": "#060d16",
		"banner.foreground": "#d0ebee",
		"banner.iconForeground": "#d0ebee",

		// button
		"button.background": "#0b1c31",
		"button.hoverBackground": "#0f2746",

		// list
		"list.hoverBackground": "#0b1c31",
		"list.dropBackground": "#0f2746",
		"list.inactiveSelectionBackground": "#0b1c31",
		"list.activeSelectionBackground": "#0b1c31",
		"list.errorForeground": "#ff2245",
		"list.warningForeground": "#ffbd2f",
	},
	"tokenColors": [
		{
			"name": "Comment",
			"scope": [
				"comment",
				"punctuation.definition.comment"
			],
			"settings": {
				"fontStyle": "italic",
				"foreground": "#395f85"
			}
		},
		{
			"name": "Variables",
			"scope": [
				"variable",
				"string constant.other.placeholder"
			],
			"settings": {
				"foreground": "#00ffaa"
			}
		},
		{
			"name": "Colors",
			"scope": [
				"constant.other.color"
			],
			"settings": {
				"foreground": "#ffffff"
			}
		},
		{
			"name": "Invalid",
			"scope": [
				"invalid",
				"invalid.illegal"
			],
			"settings": {
				"foreground": "#ff2245"
			}
		},
		{
			"name": "Keyword, Storage",
			"scope": [
				"keyword",
				"storage.type",
				"storage.modifier"
			],
			"settings": {
				"foreground": "#b23fff"
			}
		},
		{
			"name": "Operator, Misc",
			"scope": [
				"keyword.control",
				"constant.other.color",
				"punctuation",
				"meta.tag",
				"punctuation.definition.tag",
				"punctuation.separator.inheritance.php",
				"punctuation.definition.tag.html",
				"punctuation.definition.tag.begin.html",
				"punctuation.definition.tag.end.html",
				"punctuation.section.embedded",
				"keyword.other.template",
				"keyword.other.substitution"
			],
			"settings": {
				"foreground": "#41aaff"
			}
		},
		{
			"name": "Tag",
			"scope": [
				"entity.name.tag",
				"meta.tag.sgml",
				"markup.deleted.git_gutter"
			],
			"settings": {
				"foreground": "#2f82ff"
			}
		},
		{
			"name": "Function, Special Method",
			"scope": [
				"entity.name.function",
				"meta.function-call",
				"variable.function",
				"support.function",
				"keyword.other.special-method"
			],
			"settings": {
				"foreground": "#ffe96c"
			}
		},
		{
			"name": "Block Level Variables",
			"scope": [
				"meta.block variable.other"
			],
			"settings": {
				"foreground": "#c19fff"
			}
		},
		{
			"name": "Other Variable, String Link",
			"scope": [
				"support.other.variable",
				"string.other.link"
			],
			"settings": {
				"foreground": "#ff2245"
			}
		},
		{
			"name": "Number, Constant, Function Argument, Tag Attribute, Embedded",
			"scope": [
				"constant.numeric",
				"constant.language",
				"support.constant",
				"constant.character",
				"constant.escape",
				"variable.parameter",
				"keyword.other.unit",
				"keyword.other"
			],
			"settings": {
				"foreground": "#55e9ee"
			}
		},
		{
			"name": "String, Symbols, Inherited Class, Markup Heading",
			"scope": [
				"string",
				"constant.other.symbol",
				"constant.other.key",
				"entity.other.inherited-class",
				"markup.heading",
				"markup.inserted.git_gutter",
				"meta.group.braces.curly constant.other.object.key.js string.unquoted.label.js"
			],
			"settings": {
				"foreground": "#41aaff"
			}
		},
		{
			"name": "Class, Support",
			"scope": [
				"entity.name",
				"support.type",
				"support.class",
				"support.other.namespace.use.php",
				"meta.use.php",
				"support.other.namespace.php",
				"markup.changed.git_gutter",
				"support.type.sys-types"
			],
			"settings": {
				"foreground": "#2f82ff"
			}
		},
		{
			"name": "Entity Types",
			"scope": [
				"support.type"
			],
			"settings": {
				"foreground": "#5cff72"
			}
		},
		{
			"name": "CSS Class and Support",
			"scope": [
				"source.css support.type.property-name",
				"source.sass support.type.property-name",
				"source.scss support.type.property-name",
				"source.less support.type.property-name",
				"source.stylus support.type.property-name",
				"source.postcss support.type.property-name"
			],
			"settings": {
				"foreground": "#838fff"
			}
		},
		{
			"name": "Sub-methods",
			"scope": [
				"entity.name.module.js",
				"variable.import.parameter.js",
				"variable.other.class.js"
			],
			"settings": {
				"foreground": "#8f0018"
			}
		},
		{
			"name": "Language methods",
			"scope": [
				"variable.language"
			],
			"settings": {
				"fontStyle": "italic",
				"foreground": "#ff2245"
			}
		},
		{
			"name": "entity.name.method.js",
			"scope": [
				"entity.name.method.js"
			],
			"settings": {
				"fontStyle": "italic",
				"foreground": "#3374ff"
			}
		},
		{
			"name": "meta.method.js",
			"scope": [
				"meta.class-method.js entity.name.function.js",
				"variable.function.constructor"
			],
			"settings": {
				"foreground": "#3374ff"
			}
		},
		{
			"name": "Attributes",
			"scope": [
				"entity.other.attribute-name"
			],
			"settings": {
				"foreground": "#856aff"
			}
		},
		{
			"name": "HTML Attributes",
			"scope": [
				"text.html.basic entity.other.attribute-name.html",
				"text.html.basic entity.other.attribute-name"
			],
			"settings": {
				"fontStyle": "italic",
				"foreground": "#856aff"
			}
		},
		{
			"name": "CSS Classes",
			"scope": [
				"entity.other.attribute-name.class"
			],
			"settings": {
				"foreground": "#2f82ff"
			}
		},
		{
			"name": "CSS ID's",
			"scope": [
				"source.sass keyword.control"
			],
			"settings": {
				"foreground": "#2f82ff"
			}
		},
		{
			"name": "Inserted",
			"scope": [
				"markup.inserted"
			],
			"settings": {
				"foreground": "#ffff"
			}
		},
		{
			"name": "Deleted",
			"scope": [
				"markup.deleted"
			],
			"settings": {
				"foreground": "#ffff"
			}
		},
		{
			"name": "Changed",
			"scope": [
				"markup.changed"
			],
			"settings": {
				"foreground": "#ffff"
			}
		},
		{
			"name": "Regular Expressions",
			"scope": [
				"string.regexp"
			],
			"settings": {
				"foreground": "#ffff"
			}
		},
		{
			"name": "Escape Characters",
			"scope": [
				"constant.character.escape"
			],
			"settings": {
				"foreground": "#ffff"
			}
		},
		{
			"name": "URL",
			"scope": [
				"*url*",
				"*link*",
				"*uri*"
			],
			"settings": {
				"fontStyle": "underline",
				"foreground": "#0044ff"
			}
		},
		{
			"name": "Decorators",
			"scope": [
				"tag.decorator.js entity.name.tag.js",
				"tag.decorator.js punctuation.definition.tag.js"
			],
			"settings": {
				"fontStyle": "italic",
				"foreground": "#ffff"
			}
		},
		{
			"name": "ES7 Bind Operator",
			"scope": [
				"source.js constant.other.object.key.js string.unquoted.label.js"
			],
			"settings": {
				"fontStyle": "italic",
				"foreground": "#ffff"
			}
		},
		{
			"name": "JSON Key - Level 0",
			"scope": [
				"source.json meta.structure.dictionary.json support.type.property-name.json"
			],
			"settings": {
				"foreground": "#b23fff"
			}
		},
		{
			"name": "JSON Key - Level 1",
			"scope": [
				"source.json meta.structure.dictionary.json meta.structure.dictionary.value.json meta.structure.dictionary.json support.type.property-name.json"
			],
			"settings": {
				"foreground": "#7136df"
			}
		},
		{
			"name": "JSON Key - Level 2",
			"scope": [
				"source.json meta.structure.dictionary.json meta.structure.dictionary.value.json meta.structure.dictionary.json meta.structure.dictionary.value.json meta.structure.dictionary.json support.type.property-name.json"
			],
			"settings": {
				"foreground": "#4736df"
			}
		},
		{
			"name": "JSON Key - Level 3",
			"scope": [
				"source.json meta.structure.dictionary.json meta.structure.dictionary.value.json meta.structure.dictionary.json meta.structure.dictionary.value.json meta.structure.dictionary.json meta.structure.dictionary.value.json meta.structure.dictionary.json support.type.property-name.json"
			],
			"settings": {
				"foreground": "#364fdf"
			}
		},
		{
			"name": "JSON Key - Level 4",
			"scope": [
				"source.json meta.structure.dictionary.json meta.structure.dictionary.value.json meta.structure.dictionary.json meta.structure.dictionary.value.json meta.structure.dictionary.json meta.structure.dictionary.value.json meta.structure.dictionary.json meta.structure.dictionary.value.json meta.structure.dictionary.json support.type.property-name.json"
			],
			"settings": {
				"foreground": "#368ddf"
			}
		},
		{
			"name": "JSON Key - Level 5",
			"scope": [
				"source.json meta.structure.dictionary.json meta.structure.dictionary.value.json meta.structure.dictionary.json meta.structure.dictionary.value.json meta.structure.dictionary.json meta.structure.dictionary.value.json meta.structure.dictionary.json meta.structure.dictionary.value.json meta.structure.dictionary.json meta.structure.dictionary.value.json meta.structure.dictionary.json support.type.property-name.json"
			],
			"settings": {
				"foreground": "#36bddf"
			}
		},
		{
			"name": "JSON Key - Level 6",
			"scope": [
				"source.json meta.structure.dictionary.json meta.structure.dictionary.value.json meta.structure.dictionary.json meta.structure.dictionary.value.json meta.structure.dictionary.json meta.structure.dictionary.value.json meta.structure.dictionary.json meta.structure.dictionary.value.json meta.structure.dictionary.json meta.structure.dictionary.value.json meta.structure.dictionary.json meta.structure.dictionary.value.json meta.structure.dictionary.json support.type.property-name.json"
			],
			"settings": {
				"foreground": "#36d4df"
			}
		},
		{
			"name": "JSON Key - Level 7",
			"scope": [
				"source.json meta.structure.dictionary.json meta.structure.dictionary.value.json meta.structure.dictionary.json meta.structure.dictionary.value.json meta.structure.dictionary.json meta.structure.dictionary.value.json meta.structure.dictionary.json meta.structure.dictionary.value.json meta.structure.dictionary.json meta.structure.dictionary.value.json meta.structure.dictionary.json meta.structure.dictionary.value.json meta.structure.dictionary.json meta.structure.dictionary.value.json meta.structure.dictionary.json support.type.property-name.json"
			],
			"settings": {
				"foreground": "#36dfba"
			}
		},
		{
			"name": "JSON Key - Level 8",
			"scope": [
				"source.json meta.structure.dictionary.json meta.structure.dictionary.value.json meta.structure.dictionary.json meta.structure.dictionary.value.json meta.structure.dictionary.json meta.structure.dictionary.value.json meta.structure.dictionary.json meta.structure.dictionary.value.json meta.structure.dictionary.json meta.structure.dictionary.value.json meta.structure.dictionary.json meta.structure.dictionary.value.json meta.structure.dictionary.json meta.structure.dictionary.value.json meta.structure.dictionary.json meta.structure.dictionary.value.json meta.structure.dictionary.json support.type.property-name.json"
			],
			"settings": {
				"foreground": "#36df90"
			}
		},
		{
			"name": "Markdown - Plain",
			"scope": [
				"text.html.markdown",
				"punctuation.definition.list_item.markdown"
			],
			"settings": {
				"foreground": "#ffff"
			}
		},
		{
			"name": "Markdown - Markup Raw Inline",
			"scope": [
				"text.html.markdown markup.inline.raw.markdown"
			],
			"settings": {
				"foreground": "#ffff"
			}
		},
		{
			"name": "Markdown - Markup Raw Inline Punctuation",
			"scope": [
				"text.html.markdown markup.inline.raw.markdown punctuation.definition.raw.markdown"
			],
			"settings": {
				"foreground": "#ffff"
			}
		},
		{
			"name": "Markdown - Heading",
			"scope": [
				"markdown.heading",
				"markup.heading | markup.heading entity.name",
				"markup.heading.markdown punctuation.definition.heading.markdown"
			],
			"settings": {
				"foreground": "#ffff"
			}
		},
		{
			"name": "Markup - Italic",
			"scope": [
				"markup.italic"
			],
			"settings": {
				"fontStyle": "italic",
				"foreground": "#ffff"
			}
		},
		{
			"name": "Markup - Bold",
			"scope": [
				"markup.bold",
				"markup.bold string"
			],
			"settings": {
				"fontStyle": "bold",
				"foreground": "#ffff"
			}
		},
		{
			"name": "Markup - Bold-Italic",
			"scope": [
				"markup.bold markup.italic",
				"markup.italic markup.bold",
				"markup.quote markup.bold",
				"markup.bold markup.italic string",
				"markup.italic markup.bold string",
				"markup.quote markup.bold string"
			],
			"settings": {
				"fontStyle": "bold",
				"foreground": "#ffff"
			}
		},
		{
			"name": "Markup - Underline",
			"scope": [
				"markup.underline"
			],
			"settings": {
				"fontStyle": "underline",
				"foreground": "#ffff"
			}
		},
		{
			"name": "Markdown - Blockquote",
			"scope": [
				"markup.quote punctuation.definition.blockquote.markdown"
			],
			"settings": {
				"foreground": "#ffff"
			}
		},
		{
			"name": "Markup - Quote",
			"scope": [
				"markup.quote"
			],
			"settings": {
				"fontStyle": "italic"
			}
		},
		{
			"name": "Markdown - Link",
			"scope": [
				"string.other.link.title.markdown"
			],
			"settings": {
				"foreground": "#ffff"
			}
		},
		{
			"name": "Markdown - Link Description",
			"scope": [
				"string.other.link.description.title.markdown"
			],
			"settings": {
				"foreground": "#ffff"
			}
		},
		{
			"name": "Markdown - Link Anchor",
			"scope": [
				"constant.other.reference.link.markdown"
			],
			"settings": {
				"foreground": "#ffff"
			}
		},
		{
			"name": "Markup - Raw Block",
			"scope": [
				"markup.raw.block"
			],
			"settings": {
				"foreground": "#ffff"
			}
		},
		{
			"name": "Markdown - Raw Block Fenced",
			"scope": [
				"markup.raw.block.fenced.markdown"
			],
			"settings": {
				"foreground": "#00000050"
			}
		},
		{
			"name": "Markdown - Fenced Bode Block",
			"scope": [
				"punctuation.definition.fenced.markdown"
			],
			"settings": {
				"foreground": "#00000050"
			}
		},
		{
			"name": "Markdown - Fenced Bode Block Variable",
			"scope": [
				"markup.raw.block.fenced.markdown",
				"variable.language.fenced.markdown",
				"punctuation.section.class.end"
			],
			"settings": {
				"foreground": "#ffff"
			}
		},
		{
			"name": "Markdown - Fenced Language",
			"scope": [
				"variable.language.fenced.markdown"
			],
			"settings": {
				"foreground": "#ffff"
			}
		},
		{
			"name": "Markdown - Separator",
			"scope": [
				"meta.separator"
			],
			"settings": {
				"fontStyle": "bold",
				"foreground": "#ffff"
			}
		},
		{
			"name": "Markup - Table",
			"scope": [
				"markup.table"
			],
			"settings": {
				"foreground": "#ffff"
			}
		}
	]
}
